README.txt
setup.cfg
setup.py
docs/HISTORY.txt
docs/INSTALL.txt
docs/LICENSE.GPL
docs/LICENSE.txt
mfabrik/__init__.py
mfabrik.printall.egg-info/PKG-INFO
mfabrik.printall.egg-info/SOURCES.txt
mfabrik.printall.egg-info/dependency_links.txt
mfabrik.printall.egg-info/entry_points.txt
mfabrik.printall.egg-info/namespace_packages.txt
mfabrik.printall.egg-info/not-zip-safe
mfabrik.printall.egg-info/paster_plugins.txt
mfabrik.printall.egg-info/requires.txt
mfabrik.printall.egg-info/top_level.txt
mfabrik/printall/.tmp_all.pt.52797~
mfabrik/printall/__init__.py
mfabrik/printall/all.pt
mfabrik/printall/configure.zcml
mfabrik/printall/tests.py
mfabrik/printall/views.py
mfabrik/printall/profiles/default/actions.xml