Metadata-Version: 1.0
Name: mfabrik.printall
Version: 1.0.2
Summary: Print all pages in a folder with one shot
Home-page: http://webandmobile.mfabrik.com
Author: Mikko Ohtamaa
Author-email: mikko@mfabrik.com
License: GPL
Keywords: plone print
Platform: UNKNOWN
Classifier: Framework :: Plone
Classifier: Programming Language :: Python
